PyHackMD/API.py
PyHackMD/__init__.py
PyHackMD/utils.py
PyHackMD-1.0.2.dist-info/METADATA
PyHackMD-1.0.2.dist-info/WHEEL
PyHackMD-1.0.2.dist-info/top_level.txt
PyHackMD-1.0.2.dist-info/RECORD
