Metadata-Version: 2.1
Name: PyHackMD
Version: 1.0.2
Summary: Python
Home-page: https://github.com/GoatWang/PyHackMD
Author: GoatWang
Author-email: jeremy4555@yahoo.com.tw
License: UNKNOWN
Platform: UNKNOWN
Classifier: Programming Language :: Python :: 3
Classifier: License :: OSI Approved :: MIT License
Classifier: Operating System :: OS Independent
Requires-Dist: requests
